README.txt
setup.cfg
setup.py
TurboCheetah.egg-info/PKG-INFO
TurboCheetah.egg-info/SOURCES.txt
TurboCheetah.egg-info/dependency_links.txt
TurboCheetah.egg-info/entry_points.txt
TurboCheetah.egg-info/not-zip-safe
TurboCheetah.egg-info/requires.txt
TurboCheetah.egg-info/top_level.txt
turbocheetah/__init__.py
turbocheetah/cheetahsupport.py
turbocheetah/tests/__init__.py
turbocheetah/tests/extra.tmpl
turbocheetah/tests/master.tmpl
turbocheetah/tests/master2.tmpl
turbocheetah/tests/page.tmpl
turbocheetah/tests/page2.tmpl
turbocheetah/tests/simple.tmpl
turbocheetah/tests/subpage.tmpl
turbocheetah/tests/test_template.py
turbocheetah/tests/sub/__init__.py
turbocheetah/tests/sub/master.tmpl
turbocheetah/tests/sub/page.tmpl
