Metadata-Version: 1.0
Name: TurboCheetah
Version: 1.0
Summary: TurboGears plugin to support use of Cheetah templates
Home-page: http://www.turbogears.org
Author: Kevin Dangoor et al
Author-email: dangoor+turbogears@gmail.com
License: MIT
Download-URL: http://www.turbogears.org/download/
Keywords: python.templating.engines,turbogears
Platform: UNKNOWN
Classifier: Development Status :: 4 - Beta
Classifier: Framework :: TurboGears
Classifier: Environment :: Web Environment :: Buffet
Classifier: Operating System :: OS Independent
Classifier: Programming Language :: Python
Classifier: License :: OSI Approved :: MIT License
Classifier: Topic :: Software Development :: Libraries :: Python Modules
